kwargs_only.py
kwargs_only-1.1.1.dist-info/LICENSE
kwargs_only-1.1.1.dist-info/METADATA
kwargs_only-1.1.1.dist-info/WHEEL
kwargs_only-1.1.1.dist-info/top_level.txt
kwargs_only-1.1.1.dist-info/RECORD
