Metadata-Version: 2.1
Name: kwargs-only
Version: 1.1.1
Summary: A decorator to make a function accept keyword arguments only, on both Python 2 and 3.
Home-page: https://github.com/adamchainz/kwargs-only
Author: Adam Johnson
Author-email: me@adamj.eu
License: ISC License
Project-URL: Changelog, https://github.com/adamchainz/kwargs-only/blob/master/HISTORY.rst
Keywords: kwargs
Platform: UNKNOWN
Classifier: Development Status :: 7 - Inactive
Classifier: Intended Audience :: Developers
Classifier: License :: OSI Approved :: ISC License (ISCL)
Classifier: Natural Language :: English
Classifier: Operating System :: OS Independent
Classifier: Programming Language :: Python :: 2
Classifier: Programming Language :: Python :: 2.7
Classifier: Programming Language :: Python :: 3
Classifier: Programming Language :: Python :: 3.4
Classifier: Programming Language :: Python :: 3.5
Classifier: Programming Language :: Python :: 3.6
Classifier: Programming Language :: Python :: 3.7
Classifier: Programming Language :: Python :: 3.8
Requires-Python: >=2.7, !=3.0.*, !=3.1.*, !=3.2.*, !=3.3.*
